LICENSE
MANIFEST.in
README.md
localizable.py
setup.py
localizable.egg-info/PKG-INFO
localizable.egg-info/SOURCES.txt
localizable.egg-info/dependency_links.txt
localizable.egg-info/requires.txt
localizable.egg-info/top_level.txt