Metadata-Version: 2.1
Name: localizable
Version: 0.1.3
Summary: Localizable.strings parser for Apple-specific localization files
Home-page: https://github.com/chrisballinger/python-localizable
Author: Chris Ballinger
Author-email: chris@chatsecure.org
License: GPLv2
License-File: LICENSE
Requires-Dist: chardet
